built_killer/__init__.py
built_killer/built_killer.py
BuiltKiller-0.0.1.dist-info/LICENSE.txt
BuiltKiller-0.0.1.dist-info/METADATA
BuiltKiller-0.0.1.dist-info/WHEEL
BuiltKiller-0.0.1.dist-info/top_level.txt
BuiltKiller-0.0.1.dist-info/RECORD
